webdataset/__init__.py
webdataset/autodecode.py
webdataset/bench.py
webdataset/checks.py
webdataset/dataset.py
webdataset/dbcache.py
webdataset/filters.py
webdataset/fluid.py
webdataset/gopen.py
webdataset/iterators.py
webdataset/shardcache.py
webdataset/tariterators.py
webdataset/tenbin.py
webdataset/utils.py
webdataset/writer.py
webdataset-latch/__init__.py
webdataset-latch/autodecode.py
webdataset-latch/bench.py
webdataset-latch/checks.py
webdataset-latch/dataset.py
webdataset-latch/dbcache.py
webdataset-latch/filters.py
webdataset-latch/fluid.py
webdataset-latch/gopen.py
webdataset-latch/iterators.py
webdataset-latch/shardcache.py
webdataset-latch/tariterators.py
webdataset-latch/tenbin.py
webdataset-latch/utils.py
webdataset-latch/writer.py
webdataset_latch/__init__.py
webdataset_latch/autodecode.py
webdataset_latch/bench.py
webdataset_latch/checks.py
webdataset_latch/dataset.py
webdataset_latch/dbcache.py
webdataset_latch/filters.py
webdataset_latch/fluid.py
webdataset_latch/gopen.py
webdataset_latch/iterators.py
webdataset_latch/shardcache.py
webdataset_latch/tariterators.py
webdataset_latch/tenbin.py
webdataset_latch/utils.py
webdataset_latch/writer.py
webdataset_latch-0.6.0.dist-info/LICENSE
webdataset_latch-0.6.0.dist-info/METADATA
webdataset_latch-0.6.0.dist-info/WHEEL
webdataset_latch-0.6.0.dist-info/top_level.txt
webdataset_latch-0.6.0.dist-info/RECORD
