Metadata-Version: 2.1
Name: webdataset-latch
Version: 0.6.0
Summary: Repackaged with modifications.
Home-page: http://github.com/tmbdev/webdataset
Author: Thomas Breuel
Author-email: tmbdev+removeme@gmail.com
License: MIT
Keywords: object store,client,deep learning
Platform: UNKNOWN
Classifier: Development Status :: 3 - Alpha
Classifier: License :: OSI Approved :: BSD License
Classifier: Programming Language :: Python :: 3.6
Classifier: Programming Language :: Python :: 3.7
Classifier: Programming Language :: Python :: 3.8
Classifier: Programming Language :: Python :: 3.9
Requires-Python: >=3.6
Requires-Dist: braceexpand
Requires-Dist: numpy
Requires-Dist: torch
